avanza/__init__.py
avanza/client.py
avanza/constants.py
avanza/exceptions.py
avanza/ticker.py
avanza/utils.py
python_avanza-0.1.0.dist-info/licenses/LICENSE
python_avanza-0.1.0.dist-info/METADATA
python_avanza-0.1.0.dist-info/WHEEL
python_avanza-0.1.0.dist-info/top_level.txt
python_avanza-0.1.0.dist-info/RECORD
