Metadata-Version: 2.4
Name: python-avanza
Version: 0.1.0
Summary: Unofficial Python client for Avanza's API with a yfinance-style interface for stocks, ETFs, and funds
Author: ningdp2012
License: MIT
Project-URL: Repository, https://github.com/ningdp2012/python-avanza
Keywords: avanza,stock,api,finance,price,etf,fund,swedish,nordic
Classifier: Development Status :: 3 - Alpha
Classifier: Intended Audience :: Developers
Classifier: License :: OSI Approved :: MIT License
Classifier: Programming Language :: Python :: 3.10
Classifier: Programming Language :: Python :: 3.11
Classifier: Programming Language :: Python :: 3.12
Classifier: Topic :: Software Development :: Libraries :: Python Modules
Requires-Python: >=3.10
License-File: LICENSE
Requires-Dist: pandas>=2.0.0
Requires-Dist: requests>=2.31.0
Provides-Extra: dev
Requires-Dist: pytest>=7.4.0; extra == "dev"
Requires-Dist: black>=23.0.0; extra == "dev"
Requires-Dist: flake8>=6.0.0; extra == "dev"
Dynamic: license-file
